merge_csv/__init__.py
merge_csv/__main__.py
merge_csv/log.py
merge_csv/merge_dataframes.py
merge_csv/merge_files.py
merge_csv/output_file.py
merge_csv/validate_options.py
merge_csv_xjg-0.0.6.dist-info/LICENSE
merge_csv_xjg-0.0.6.dist-info/METADATA
merge_csv_xjg-0.0.6.dist-info/WHEEL
merge_csv_xjg-0.0.6.dist-info/entry_points.txt
merge_csv_xjg-0.0.6.dist-info/top_level.txt
merge_csv_xjg-0.0.6.dist-info/RECORD
