Metadata-Version: 2.1
Name: merge-csv-xjg
Version: 0.0.6
Summary: Merge two CSV files with pandas
Home-page: https://github.com/JoaquimXG/csv-merge
Author: Joaquim Gomez
License: UNKNOWN
Platform: UNKNOWN
Classifier: Programming Language :: Python :: 3
Classifier: License :: OSI Approved :: MIT License
Classifier: Operating System :: OS Independent
Requires-Python: >=3.6
License-File: LICENSE
Requires-Dist: pandas
Requires-Dist: numpy
Requires-Dist: click
